gsdk/__init__.py
gsdk/test.py
gsdk/auth/__init__.py
gsdk/auth/jwt.py
gsdk/client/__init__.py
gsdk/integrations/__init__.py
gsdk/integrations/sportsdataio/__init__.py
gsdk/integrations/sportsdataio/sportsdataio_meta.py
gsdk/integrations/sportsdataio/ncaab/__init__.py
gsdk/integrations/sportsdataio/ncaab/ncaab.py
gsdk/integrations/sportsdataio/ncaab/ncaablike.py
gsdk/integrations/sportsdataio/ncaab/game/__init__.py
gsdk/integrations/sportsdataio/ncaab/game/by_date.py
gsdk/integrations/sportsdataio/ncaab/game/by_date_like.py
gsdk/integrations/sportsdataio/ncaab/game/games.py
gsdk/integrations/sportsdataio/ncaab/game/gameslike.py
gsdk/integrations/sportsdataio/ncaab/team/__init__.py
gsdk/integrations/sportsdataio/ncaab/team/team.py
gsdk/integrations/sportsdataio/ncaab/team/teamlike.py
gsdk/models/__init__.py
gsdk/models/ncaab/__init__.py
gsdk/models/ncaab/division/__init__.py
gsdk/models/ncaab/division/division.py
gsdk/models/ncaab/division/divisionlike.py
gsdk/models/ncaab/division/efficiency.py
gsdk/models/ncaab/division/efficiencylike.py
gsdk/models/ncaab/game/__init__.py
gsdk/models/ncaab/game/game.py
gsdk/models/ncaab/game/gamelike.py
gsdk/models/ncaab/team/__init__.py
gsdk/models/ncaab/team/efficiency.py
gsdk/models/ncaab/team/efficiencylike.py
gsdk/models/ncaab/team/team.py
gsdk/models/ncaab/team/teamlike.py
gsdk/models/ncaab/v1/__init__.py
gsdk/models/ncaab/v1/controllers/__init__.py
gsdk/models/ncaab/v1/controllers/api.py
gsdk/models/ncaab/v1/controllers/controller.py
gsdk/models/ncaab/v1/controllers/models.py
gsdk/utils/__init__.py
gsdk/utils/pytorch/__init__.py
gameday_guru_sdk-0.0.17.dist-info/METADATA
gameday_guru_sdk-0.0.17.dist-info/WHEEL
gameday_guru_sdk-0.0.17.dist-info/entry_points.txt
gameday_guru_sdk-0.0.17.dist-info/top_level.txt
gameday_guru_sdk-0.0.17.dist-info/RECORD
