Metadata-Version: 2.1
Name: gameday-guru-sdk
Version: 0.0.17
Summary: The Gameday Guru SDK
Home-page: https://github.com/realpython/reader
Author: Real Python
Author-email: info@realpython.com
License: MIT
Platform: UNKNOWN
Classifier: License :: OSI Approved :: MIT License
Classifier: Programming Language :: Python :: 3
Classifier: Programming Language :: Python :: 3.9
Requires-Dist: atlastk (==0.13)
Requires-Dist: bleach (==4.1.0)
Requires-Dist: certifi (==2021.10.8)
Requires-Dist: charset-normalizer (==2.0.12)
Requires-Dist: colorama (==0.4.4)
Requires-Dist: Deprecated (==1.2.13)
Requires-Dist: docutils (==0.18.1)
Requires-Dist: idna (==3.3)
Requires-Dist: importlib-metadata (==4.11.2)
Requires-Dist: keyring (==23.5.0)
Requires-Dist: numpy (==1.22.2)
Requires-Dist: packaging (==21.3)
Requires-Dist: Pillow (==9.0.1)
Requires-Dist: pkginfo (==1.8.2)
Requires-Dist: pony (==0.7.16)
Requires-Dist: Pygments (==2.11.2)
Requires-Dist: PyJWT (==2.3.0)
Requires-Dist: pyparsing (==3.0.7)
Requires-Dist: python-dateutil (==2.8.2)
Requires-Dist: python-dotenv (==0.19.2)
Requires-Dist: readme-renderer (==32.0)
Requires-Dist: redis (==4.1.4)
Requires-Dist: requests (==2.27.1)
Requires-Dist: requests-toolbelt (==0.9.1)
Requires-Dist: rfc3986 (==2.0.0)
Requires-Dist: six (==1.16.0)
Requires-Dist: SQLAlchemy (==1.4.32)
Requires-Dist: torch (==1.10.2)
Requires-Dist: torchaudio (==0.10.2)
Requires-Dist: torchvision (==0.11.3)
Requires-Dist: tortoise (==0.1.1)
Requires-Dist: tqdm (==4.63.0)
Requires-Dist: twine (==3.8.0)
Requires-Dist: types-cryptography (==3.3.15)
Requires-Dist: types-enum34 (==1.1.8)
Requires-Dist: types-ipaddress (==1.0.8)
Requires-Dist: types-PyJWT (==1.7.1)
Requires-Dist: types-redis (==4.1.17)
Requires-Dist: typing-extensions (==4.1.1)
Requires-Dist: urllib3 (==1.26.8)
Requires-Dist: webencodings (==0.5.1)
Requires-Dist: wrapt (==1.14.0)
Requires-Dist: zipp (==3.7.0)
